setup.py
distribution_calculator/Binomialdistribution.py
distribution_calculator/Gaussiandistribution.py
distribution_calculator/Generaldistribution.py
distribution_calculator/__init__.py
distribution_calculator.egg-info/PKG-INFO
distribution_calculator.egg-info/SOURCES.txt
distribution_calculator.egg-info/dependency_links.txt
distribution_calculator.egg-info/not-zip-safe
distribution_calculator.egg-info/top_level.txt