Metadata-Version: 1.0
Name: distribution-calculator
Version: 0.1
Summary: Gaussian and Binomial distributions
Home-page: UNKNOWN
Author: Sumeet Sarode
Author-email: UNKNOWN
License: UNKNOWN
Platform: UNKNOWN
